{
  "event_id": "evt-123213",
  "form_response": {
    "form_id": "formzmckldmkal",
    "token": "tok-2",
    "hidden": { "email": "testerabc123@example.com" },
    "answers": [
      { "type": "text",    "text": " Alina",                 "field": { "ref": "name" } },
      { "type": "choice",  "choice": { "label": "Junior" },     "field": { "ref": "career_level" } },
      { "type": "email",    "email": "testerabc123@example.com",                 "field": { "ref": "email" } },
      { "type": "text",    "text": "Backend SWE in 2 months",   "field": { "ref": "career_goal" } },
      { "type": "choice",  "choice": { "label": "Tech" },       "field": { "ref": "industry" } },
      { "type": "text",    "text": "Backend Engineer",          "field": { "ref": "target_role" } },
      { "type": "choices", "choices": { "labels": ["Python","AWS","Postgres"] }, "field": { "ref": "skills" } },
      { "type": "choices", "choices": { "labels": ["Focus","System design"] },   "field": { "ref": "career_challenges" } },
      { "type": "choice",  "choice": { "label": "Direct feedback" },             "field": { "ref": "coaching_style" } },
      { "type": "choice",  "choice": { "label": "2 months" },                    "field": { "ref": "target_timeline" } },
      { "type": "choice",  "choice": { "label": "2 hrs/day" },                   "field": { "ref": "study_time" } },
      { "type": "choice",  "choice": { "label": "Works well under pressure" },   "field": { "ref": "pressure_response" } }
    ]
  }
}
